kb_cchook/__init__.py
kb_cchook/constants.py
kb_cchook/exceptions.py
kb_cchook/hook.py
kb_cchook/validators.py
kb_cchook-0.1.0.dist-info/WHEEL
kb_cchook-0.1.0.dist-info/entry_points.txt
kb_cchook-0.1.0.dist-info/METADATA
kb_cchook-0.1.0.dist-info/RECORD
