Metadata-Version: 2.3
Name: kb-cchook
Version: 0.1.0
Summary: Claude Code hook
Author: Ken Banks
Author-email: Ken Banks <kenbanks.peng@gmail.com>
Requires-Python: >=3.13
